cac_jira/__init__.py
cac_jira/cli/main.py
cac_jira/commands/command.py
cac_jira/commands/issue/__init__.py
cac_jira/commands/issue/assign.py
cac_jira/commands/issue/attach.py
cac_jira/commands/issue/begin.py
cac_jira/commands/issue/block.py
cac_jira/commands/issue/browse.py
cac_jira/commands/issue/close.py
cac_jira/commands/issue/comment.py
cac_jira/commands/issue/create.py
cac_jira/commands/issue/delete.py
cac_jira/commands/issue/fields.py
cac_jira/commands/issue/label.py
cac_jira/commands/issue/list.py
cac_jira/commands/issue/show.py
cac_jira/commands/issue/update.py
cac_jira/commands/project/__init__.py
cac_jira/commands/project/list.py
cac_jira/commands/project/show.py
cac_jira/config/cac_jira.yaml
cac_jira/core/client.py
cac_jira-0.6.0.dist-info/licenses/LICENSE
cac_jira-0.6.0.dist-info/METADATA
cac_jira-0.6.0.dist-info/WHEEL
cac_jira-0.6.0.dist-info/entry_points.txt
cac_jira-0.6.0.dist-info/top_level.txt
cac_jira-0.6.0.dist-info/RECORD
