Metadata-Version: 2.4
Name: cac-jira
Version: 0.6.0
Summary: A command-line interface for interacting with Jira
Author-email: Ryan Punt <ryan@mirum.org>
License-Expression: MIT
Project-URL: homepage, https://mirum.org/cac-jira/
Project-URL: repository, https://github.com/rpunt/cac-jira
Keywords: jira,cli,atlassian,project-management,command-lint,python,cli-tool
Classifier: Programming Language :: Python :: 3
Classifier: Operating System :: OS Independent
Requires-Python: <4.0,>=3.10
License-File: LICENSE
Requires-Dist: cac-core<1.0.0,>=0.5.0
Requires-Dist: tabulate>=0.9.0
Requires-Dist: jira<4.0.0,>=3.10.5
Requires-Dist: pyyaml>=6.0.2
Requires-Dist: keyring>=25.5.0
Requires-Dist: argcomplete>=3.6.2
Provides-Extra: dev
Requires-Dist: mypy>=1.3.0; extra == "dev"
Requires-Dist: types-pyyaml>=6.0.12; extra == "dev"
Requires-Dist: types-tabulate>=0.9.0; extra == "dev"
Provides-Extra: test
Requires-Dist: pytest>=7.3.1; extra == "test"
Provides-Extra: lint
Requires-Dist: black<25.0,>=23.3; extra == "lint"
Requires-Dist: isort>=5.12.0; extra == "lint"
Requires-Dist: pylint>=2.17.0; extra == "lint"
Provides-Extra: docs
Requires-Dist: sphinx>=7.0.0; extra == "docs"
Requires-Dist: sphinx-rtd-theme>=1.2.0; extra == "docs"
Provides-Extra: all
Requires-Dist: mypy>=1.3.0; extra == "all"
Requires-Dist: types-pyyaml>=6.0.12; extra == "all"
Requires-Dist: types-tabulate>=0.9.0; extra == "all"
Requires-Dist: pytest>=7.3.1; extra == "all"
Requires-Dist: black<25.0,>=23.3; extra == "all"
Requires-Dist: isort>=5.12.0; extra == "all"
Requires-Dist: pylint>=2.17.0; extra == "all"
Requires-Dist: sphinx>=7.0.0; extra == "all"
Requires-Dist: sphinx-rtd-theme>=1.2.0; extra == "all"
Dynamic: license-file
